[
    {"id": 1, "firstName": "Rakesh", "lastName": "Sharma", "phoneNumbers": [11111,2222222,333333,44444]},
    {"id": 2, "firstName": "Mit", "lastName": "Patel", "phoneNumbers": [11111,2222222,333333,44444]},
    {"id": 3, "firstName": "Ritesh", "lastName": "Chawan", "phoneNumbers": [11111,2222222,333333,44444]},
    {"id": 4, "firstName": "Rohini", "lastName": "Patel", "phoneNumbers": [11111,2222222,333333,44444]},
    {"id": 5, "firstName": "Rakesh", "lastName": "Sharma", "phoneNumbers": [11111,2222222,333333,44444]},
    {"id": 6, "firstName": "Mit", "lastName": "Patel", "phoneNumbers": [11111,2222222,333333,44444]},
    {"id": 7, "firstName": "Ritesh", "lastName": "Chawan", "phoneNumbers": [11111,2222222,333333,44444]},
    {"id": 8, "firstName": "Rohini", "lastName": "Patel", "phoneNumbers": [11111,2222222,333333,44444]},
    {"id": 9, "firstName": "Rakesh", "lastName": "Sharma", "phoneNumbers": [11111,2222222,333333,44444]},
    {"id": 10, "firstName": "Mit", "lastName": "Patel", "phoneNumbers": [11111,2222222,333333,44444]},
    {"id": 11, "firstName": "Ritesh", "lastName": "Chawan", "phoneNumbers": [11111,2222222,333333,44444]},
    {"id": 12, "firstName": "Rohini", "lastName": "Patel", "phoneNumbers": [11111,2222222,333333,44444]},
    {"id": 13, "firstName": "Rakesh", "lastName": "Sharma", "phoneNumbers": [11111,2222222,333333,44444]},
    {"id": 14, "firstName": "Mit", "lastName": "Patel", "phoneNumbers": [11111,2222222,333333,44444]},
    {"id": 15, "firstName": "Ritesh", "lastName": "Chawan", "phoneNumbers": [11111,2222222,333333,44444]},
    {"id": 16, "firstName": "Rohini", "lastName": "Patel", "phoneNumbers": [11111,2222222,333333,44444]},
    {"id": 17, "firstName": "Rakesh", "lastName": "Sharma", "phoneNumbers": [11111,2222222,333333,44444]},
    {"id": 18, "firstName": "Mit", "lastName": "Patel", "phoneNumbers": [11111,2222222,333333,44444]},
    {"id": 19, "firstName": "Ritesh", "lastName": "Chawan", "phoneNumbers": [11111,2222222,333333,44444]},
    {"id": 20, "firstName": "Rohini", "lastName": "Patel", "phoneNumbers": [11111,2222222,333333,44444]}
]